pyhtz/__init__.py
pyhtz/async_/async_embedder.py
pyhtz/async_/async_manager.py
pyhtz/embeddings/encoder.py
pyhtz/sql_template/generate_template.py
pyhtz/storage/bq_manager.py
pyhtz/storage/mongo_manager.py
pyhtz/vdb/qdrant_manager.py
pyhtz-0.1.17.dist-info/METADATA
pyhtz-0.1.17.dist-info/WHEEL
pyhtz-0.1.17.dist-info/RECORD
