Metadata-Version: 2.1
Name: pyhtz
Version: 0.1.17
Summary: 
Author: moti dabastani
Author-email: moti.dabastani@themarker.com
Requires-Python: >=3.9,<4.0
Classifier: Programming Language :: Python :: 3
Classifier: Programming Language :: Python :: 3.9
Classifier: Programming Language :: Python :: 3.10
Classifier: Programming Language :: Python :: 3.11
Classifier: Programming Language :: Python :: 3.12
Requires-Dist: google-cloud-bigquery (>=3.24.0,<4.0.0)
Requires-Dist: google-cloud-bigquery-storage (>=2.25.0,<3.0.0)
Requires-Dist: google-cloud-storage (>=2.16.0,<3.0.0)
Requires-Dist: jinja2 (>=3.1.4,<4.0.0)
Requires-Dist: pandas (>=2.2.2,<3.0.0)
Requires-Dist: polars (>=1.0.0)
Requires-Dist: pyarrow (>=16.1.0,<17.0.0)
Requires-Dist: pymongo (>=4.7.3,<5.0.0)
Requires-Dist: qdrant-client (>=1.9.1,<2.0.0)
Requires-Dist: retry (>=0.9.2,<0.10.0)
Requires-Dist: vertexai (>=1.49.0,<2.0.0)
